facef/__init__.py
facef/detection.py
facef/distance.py
facef/extraction.py
facef/utils/__init__.py
facef/utils/model_utils.py
facef/utils/ultra_light.py
facef/utils/mtcnntf/__init__.py
facef/utils/mtcnntf/models.py
facef/utils/mtcnntf/utils.py
facef-0.1.5.dist-info/LICENSE
facef-0.1.5.dist-info/METADATA
facef-0.1.5.dist-info/WHEEL
facef-0.1.5.dist-info/top_level.txt
facef-0.1.5.dist-info/RECORD
