Metadata-Version: 2.1
Name: facef
Version: 0.1.5
Summary: face recognition library, flexible and easy to use
Home-page: https://github.com/DuyKK/duyai
Author: Duy Nguyen Manh
Author-email: manhduy160396@email.com
License: MIT License
Platform: UNKNOWN
License-File: LICENSE
Requires-Dist: opencv-python
Requires-Dist: gdown
